<?xml version="1.0" encoding="UTF-8"?>
<databaseChangeLog
        xmlns="http://www.liquibase.org/xml/ns/dbchangelog"
        xmlns:xsi="http://www.w3.org/2001/XMLSchema-instance"
        xsi:schemaLocation="http://www.liquibase.org/xml/ns/dbchangelog
        http://www.liquibase.org/xml/ns/dbchangelog/dbchangelog-3.8.xsd">

    <include file="/db/changelog/user/user.changelog-1.0.xml"/>
    <include file="/db/changelog/user/user.changelog-1.1.xml"/>
    <include file="/db/changelog/activation_token/activation_token.changelog-1.0.xml"/>
    <include file="/db/changelog/activation_token/activation_token.changelog-1.1.xml"/>
    <include file="/db/changelog/device/device.changelog-1.0.xml"/>
    <include file="/db/changelog/user/user.changelog-1.2.xml"/>
    <include file="/db/changelog/reset_password_token/reset_password_token.changelog-1.0.xml"/>
    <include file="/db/changelog/reset_password_token/reset_password_token.changelog-1.1.xml"/>
    <include file="/db/changelog/device/device.changelog-1.1.xml" />
    <include file="/db/changelog/device/device.changelog-1.2.xml" />
    <include file="/db/changelog/fixtures/fixtures.changelog-1.0.xml" />
    <include file="/db/changelog/notification/notification.changelog-1.0.xml" />
    <include file="/db/changelog/notification/notification.changelog-1.1.xml" />
    <include file="/db/changelog/fixtures/fixtures.changelog-1.1.xml" />
    <include file="db/changelog/measurement/measurement.changelog-1.0.xml" />
    <include file="db/changelog/ai_service_notification/ai_service_notification.changelog-1.0.xml" />
    <include file="db/changelog/notification_images/notification_images.changelog-1.0.xml" />
</databaseChangeLog>